zc/relationship/README.rst
zc/relationship/__init__.py
zc/relationship/container.rst
zc/relationship/index.py
zc/relationship/interfaces.py
zc/relationship/intid.py
zc/relationship/keyref.py
zc/relationship/shared.py
zc/relationship/tests.py
zc_relationship-3.0.dist-info/licenses/LICENSE.txt
zc_relationship-3.0.dist-info/METADATA
zc_relationship-3.0.dist-info/WHEEL
zc_relationship-3.0.dist-info/top_level.txt
zc_relationship-3.0.dist-info/RECORD
