Metadata-Version: 2.4
Name: zc.relationship
Version: 3.0
Summary: Zope 3 relationship index.  Precursor to zc.relation.
Home-page: https://github.com/zopefoundation/zc.relationship
Author: Gary Poster
Author-email: zope-dev@zope.dev
License: ZPL-2.1
Keywords: zope zope3
Classifier: Programming Language :: Python :: 3
Classifier: Programming Language :: Python :: 3.9
Classifier: Programming Language :: Python :: 3.10
Classifier: Programming Language :: Python :: 3.11
Classifier: Programming Language :: Python :: 3.12
Classifier: Programming Language :: Python :: 3.13
Classifier: Programming Language :: Python :: Implementation :: CPython
Classifier: License :: OSI Approved :: Zope Public License
Requires-Python: >=3.9
License-File: LICENSE.txt
Requires-Dist: ZODB3>=3.8dev
Requires-Dist: zope.app.container
Requires-Dist: zope.app.intid
Requires-Dist: zope.interface
Requires-Dist: zope.component
Requires-Dist: zope.app.keyreference
Requires-Dist: zope.location
Requires-Dist: zope.index
Requires-Dist: zc.relation>=1.1
Requires-Dist: zope.app.testing
Requires-Dist: zope.app.component
Requires-Dist: zope.testing
Requires-Dist: setuptools
Provides-Extra: test
Requires-Dist: zope.app.folder; extra == "test"
Dynamic: author
Dynamic: author-email
Dynamic: classifier
Dynamic: description
Dynamic: home-page
Dynamic: keywords
Dynamic: license
Dynamic: license-file
Dynamic: provides-extra
Dynamic: requires-dist
Dynamic: requires-python
Dynamic: summary
